Workbook

Sheet Scenarios
B2: Sr. No | C2: Assumptions
B3: 1 | C3: There are 30 days in a month
B4: 2 | C4: Year comprise of 360 days
B5: 3 | C5: Due date is fixed for all customers on 5th of every month
B6: 4 | C6: All are rounded values, no collection in paise. Example if Interest computation results in 30282.20, collection will be for 30282 and vice versa if interest collection results in30282.70, it will result in 30283
B7: 5 | C7: There are no penalities charged to the customer incase of default
B9: Sr. No | C9: Scenarios
B10: 1 | C10: Disbursement and due date is on same day i.e. Exactly 30 days part
B11: 2 | C11: Disbursement is on or before 15 th of month
B12: 3 | C12: Disbursement is after 15th of month
B13: 4 | C13: Loan is deffered for 3 months
B14: 5 | C14: PartPayment is made during BPI Period | D14: Reduction of Tenure, keeping Installment same
B15: 6 | C15: PartPayment is made after BPI Period is completed
B16: 7 | C16: Foreclosure of loan
B17: 8 | C17: One time settlement and Write off Loan

Sheet Disbursement and due date same
A1: Scenario 1 | B1: Due date and Disbursement date is on same day
B2: Date of Disbursement | C2: 46144 | E2: 1st Due Date | F2: 46175
B3: Profit / Rental % | C3: 0.11 | E3: Maturity Date | F3: =C59 -> 47605
B4: Vehicle Cost | C4: 51400 | E4: PMT | F4: =PMT(C3/12,C6,-F5) -> 1070.0046
B5: Downpayment | C5: =10000 -> 10000 | E5: Loan Amount | F5: =C4-C5 -> 41400
B6: Tenure | C6: 48 | D6: Months
B10: Sr. No | C10: Date | D10: No. of days | E10: PMT | F10: Rental Recovered | G10: Principal Recovered | H10: Principal o/s | I10: Blox's Share | J10: Customer's Share
B11: 0 | C11: =$C$2 -> 46144 | H11: =$F$5 -> 41400 | I11: =(H11/$C$4) -> 0.80544747 | J11: =20% -> 0.2
B12: 1 | C12: 46175 | D12: =C12-C11 -> 31 | E12: =$F$4 -> 1070.0046 | F12: =$H11*$C$3/12 -> 379.5 | G12: =E12-F12 -> 690.50464 | H12: =H11-G12 -> 40709.495 | I12: =(H12/$C$4) -> 0.79201353 | J12: =100%-I12 -> 0.20798647
B13: 2 | C13: 46205 | D13: =C13-C12 -> 30 | E13: =$F$4 -> 1070.0046 | F13: =$H12*$C$3/12 -> 373.17037 | G13: =E13-F13 -> 696.83426 | H13: =H12-G13 -> 40012.661 | I13: =(H13/$C$4) -> 0.77845644 | J13: =100%-I13 -> 0.22154356
B14: 3 | C14: 46236 | D14: =C14-C13 -> 31 | E14: =$F$4 -> 1070.0046 | F14: =$H13*$C$3/12 -> 366.78273 | G14: =E14-F14 -> 703.22191 | H14: =H13-G14 -> 39309.439 | I14: =(H14/$C$4) -> 0.76477508 | J14: =100%-I14 -> 0.23522492
B15: 4 | C15: 46267 | D15: =C15-C14 -> 31 | E15: =$F$4 -> 1070.0046 | F15: =$H14*$C$3/12 -> 360.33653 | G15: =E15-F15 -> 709.66811 | H15: =H14-G15 -> 38599.771 | I15: =(H15/$C$4) -> 0.75096831 | J15: =100%-I15 -> 0.24903169
B16: 5 | C16: 46297 | D16: =C16-C15 -> 30 | E16: =$F$4 -> 1070.0046 | F16: =$H15*$C$3/12 -> 353.83123 | G16: =E16-F16 -> 716.1734 | H16: =H15-G16 -> 37883.598 | I16: =(H16/$C$4) -> 0.73703497 | J16: =100%-I16 -> 0.26296503
B17: 6 | C17: 46328 | D17: =C17-C16 -> 31 | E17: =$F$4 -> 1070.0046 | F17: =$H16*$C$3/12 -> 347.26631 | G17: =E17-F17 -> 722.73832 | H17: =H16-G17 -> 37160.859 | I17: =(H17/$C$4) -> 0.72297392 | J17: =100%-I17 -> 0.27702608
B18: 7 | C18: 46358 | D18: =C18-C17 -> 30 | E18: =$F$4 -> 1070.0046 | F18: =$H17*$C$3/12 -> 340.64121 | G18: =E18-F18 -> 729.36343 | H18: =H17-G18 -> 36431.496 | I18: =(H18/$C$4) -> 0.70878397 | J18: =100%-I18 -> 0.29121603
B19: 8 | C19: 46389 | D19: =C19-C18 -> 31 | E19: =$F$4 -> 1070.0046 | F19: =$H18*$C$3/12 -> 333.95538 | G19: =E19-F19 -> 736.04926 | H19: =H18-G19 -> 35695.447 | I19: =(H19/$C$4) -> 0.69446394 | J19: =100%-I19 -> 0.30553606
B20: 9 | C20: 46420 | D20: =C20-C19 -> 31 | E20: =$F$4 -> 1070.0046 | F20: =$H19*$C$3/12 -> 327.20826 | G20: =E20-F20 -> 742.79637 | H20: =H19-G20 -> 34952.65 | I20: =(H20/$C$4) -> 0.68001265 | J20: =100%-I20 -> 0.31998735
B21: 10 | C21: 46448 | D21: =C21-C20 -> 28 | E21: =$F$4 -> 1070.0046 | F21: =$H20*$C$3/12 -> 320.39929 | G21: =E21-F21 -> 749.60534 | H21: =H20-G21 -> 34203.045 | I21: =(H21/$C$4) -> 0.66542889 | J21: =100%-I21 -> 0.33457111
B22: 11 | C22: 46479 | D22: =C22-C21 -> 31 | E22: =$F$4 -> 1070.0046 | F22: =$H21*$C$3/12 -> 313.52791 | G22: =E22-F22 -> 756.47672 | H22: =H21-G22 -> 33446.568 | I22: =(H22/$C$4) -> 0.65071144 | J22: =100%-I22 -> 0.34928856
B23: 12 | C23: 46509 | D23: =C23-C22 -> 30 | E23: =$F$4 -> 1070.0046 | F23: =$H22*$C$3/12 -> 306.59354 | G23: =E23-F23 -> 763.41109 | H23: =H22-G23 -> 32683.157 | I23: =(H23/$C$4) -> 0.63585909 | J23: =100%-I23 -> 0.36414091
... B59: 48 | C59: 47605 | D59: =C59-C58 -> 30 | E59: =$F$4 -> 1070.0046 | F59: =$H58*$C$3/12 -> 9.7192824 | G59: =E59-F59 -> 1060.2854 | H59: =H58-G59 -> 4.0927262e-12 | I59: =(H59/$C$4) -> 7.9625023e-17 | J59: =100%-I59 -> 1

Sheet Disbursement before 15
A1: Scenario 2 | B1: Disbursement is on or before 15th of month
A2: Date of Disbursement | B2: 46157 | D2: 1st Due Date | E2: 46175
A3: Profit / Rental % | B3: 0.1 | D3: PMT | E3: =PMT(B3/12,B6,-E5) -> 25813.75
A4: Vehicle Cost | B4: 1000000 | D4: No. of Days (Between disbursement and due date) - BPI | E4: =E2-B2 -> 18
A5: Downpayment | B5: =20%*B4 -> 200000 | D5: Loan Amount | E5: =B4-B5 -> 800000
A6: Tenure | B6: 36 | C6: Months
A10: Sr. No | B10: Date | C10: No. of days | D10: PMT | E10: Profit / Rental Recovered | F10: Principal Recovered | G10: Principal o/s | H10: Blox's Share | I10: Customer's Share
A11: 0 | B11: =$B$2 -> 46157 | G11: =$E$5 -> 800000 | H11: =G11/$B$4 -> 0.8 | I11: =1-H11 -> 0.2
A12: 1 | B12: =E2 -> 46175 | C12: =B12-B11 -> 18 | D12: =$E$3 -> 25813.75 | E12: =G11*B3/12*C12/30 -> 4000 | F12: =D12-E12 -> 21813.75 | G12: =G11-F12 -> 778186.25 | H12: =G12/$B$4 -> 0.77818625 | I12: =1-H12 -> 0.22181375
A13: 2 | B13: 46205 | C13: =B13-B12 -> 30 | D13: =$E$3 -> 25813.75 | E13: =G12*$B$3/12 -> 6484.8854 | F13: =D13-E13 -> 19328.864 | G13: =G12-F13 -> 758857.39 | H13: =G13/$B$4 -> 0.75885739 | I13: =1-H13 -> 0.24114261
A14: 3 | B14: 46236 | C14: =B14-B13 -> 31 | D14: =$E$3 -> 25813.75 | E14: =G13*$B$3/12 -> 6323.8115 | F14: =D14-E14 -> 19489.938 | G14: =G13-F14 -> 739367.45 | H14: =G14/$B$4 -> 0.73936745 | I14: =1-H14 -> 0.26063255
A15: 4 | B15: 46267 | C15: =B15-B14 -> 31 | D15: =$E$3 -> 25813.75 | E15: =G14*$B$3/12 -> 6161.3954 | F15: =D15-E15 -> 19652.354 | G15: =G14-F15 -> 719715.09 | H15: =G15/$B$4 -> 0.71971509 | I15: =1-H15 -> 0.28028491
A16: 5 | B16: 46297 | C16: =B16-B15 -> 30 | D16: =$E$3 -> 25813.75 | E16: =G15*$B$3/12 -> 5997.6258 | F16: =D16-E16 -> 19816.124 | G16: =G15-F16 -> 699898.97 | H16: =G16/$B$4 -> 0.69989897 | I16: =1-H16 -> 0.30010103
A17: 6 | B17: 46328 | C17: =B17-B16 -> 31 | D17: =$E$3 -> 25813.75 | E17: =G16*$B$3/12 -> 5832.4914 | F17: =D17-E17 -> 19981.258 | G17: =G16-F17 -> 679917.71 | H17: =G17/$B$4 -> 0.67991771 | I17: =1-H17 -> 0.32008229
A18: 7 | B18: 46358 | C18: =B18-B17 -> 30 | D18: =$E$3 -> 25813.75 | E18: =G17*$B$3/12 -> 5665.9809 | F18: =D18-E18 -> 20147.769 | G18: =G17-F18 -> 659769.94 | H18: =G18/$B$4 -> 0.65976994 | I18: =1-H18 -> 0.34023006
A19: 8 | B19: 46389 | C19: =B19-B18 -> 31 | D19: =$E$3 -> 25813.75 | E19: =G18*$B$3/12 -> 5498.0829 | F19: =D19-E19 -> 20315.667 | G19: =G18-F19 -> 639454.28 | H19: =G19/$B$4 -> 0.63945428 | I19: =1-H19 -> 0.36054572
A20: 9 | B20: 46420 | C20: =B20-B19 -> 31 | D20: =$E$3 -> 25813.75 | E20: =G19*$B$3/12 -> 5328.7856 | F20: =D20-E20 -> 20484.964 | G20: =G19-F20 -> 618969.31 | H20: =G20/$B$4 -> 0.61896931 | I20: =1-H20 -> 0.38103069
A21: 10 | B21: 46448 | C21: =B21-B20 -> 28 | D21: =$E$3 -> 25813.75 | E21: =G20*$B$3/12 -> 5158.0776 | F21: =D21-E21 -> 20655.672 | G21: =G20-F21 -> 598313.64 | H21: =G21/$B$4 -> 0.59831364 | I21: =1-H21 -> 0.40168636
A22: 11 | B22: 46479 | C22: =B22-B21 -> 31 | D22: =$E$3 -> 25813.75 | E22: =G21*$B$3/12 -> 4985.947 | F22: =D22-E22 -> 20827.803 | G22: =G21-F22 -> 577485.84 | H22: =G22/$B$4 -> 0.57748584 | I22: =1-H22 -> 0.42251416
A23: 12 | B23: 46509 | C23: =B23-B22 -> 30 | D23: =$E$3 -> 25813.75 | E23: =G22*$B$3/12 -> 4812.382 | F23: =D23-E23 -> 21001.368 | G23: =G22-F23 -> 556484.47 | H23: =G23/$B$4 -> 0.55648447 | I23: =1-H23 -> 0.44351553
A24: 13 | B24: 46540 | C24: =B24-B23 -> 31 | D24: =$E$3 -> 25813.75 | E24: =G23*$B$3/12 -> 4637.3706 | F24: =D24-E24 -> 21176.379 | G24: =G23-F24 -> 535308.09 | H24: =G24/$B$4 -> 0.53530809 | I24: =1-H24 -> 0.46469191
... A46: 35 | B46: 47210 | C46: =B46-B45 -> 31 | D46: =$E$3 -> 25813.75 | E46: =G45*$B$3/12 -> 395.68752 | F46: =D46-E46 -> 25418.062 | G46: =G45-F46 -> 22064.44 | H46: =G46/$B$4 -> 0.02206444 | I46: =1-H46 -> 0.97793556
A47: 36 | B47: 47240 | C47: =B47-B46 -> 30 | D47: =$E$3-3565 -> 22248.75 | E47: =G46*$B$3/12 -> 183.87033 | F47: =D47-E47 -> 22064.879 | G47: =G46-F47 -> -0.43958326 | H47: =G47/$B$4 -> -4.3958326e-07 | I47: =1-H47 -> 1.0000004

Sheet Disbursement after 15
A1: Scenario 3 | B1: Disbursement is after 15th of month(excluding 15th)
A2: Date of Disbursement | B2: 46162 | D2: 1st Due Date | E2: 46205
A3: Profit / Rental % | B3: 0.1 | D3: PMT | E3: =PMT(B3/12,B6,-E5) -> 1326.8267
A4: Vehicle Cost | B4: ='Disbursement and due date same'!C4 -> 51400 | D4: No. of Days (Between disbursement and due date) | E4: =E2-B2 -> 43
A5: Downpayment | B5: =20%*B4 -> 10280 | D5: Loan Amount | E5: =B4-B5 -> 41120
A6: Tenure | B6: 36 | C6: Months | D6: Impact | E6: 1. BPI is collected with 1st installment due keeping EMI Constant 2. Odd amount is adjusted in last installment
A9: BPI is collected with 1st installment due keeping EMI Constant
A10: Sr. No | B10: Date | C10: No. of days | D10: PMT | E10: Profit / Rental | F10: Principal Recovered | G10: Principal o/s | H10: Blox's Ownership | I10: Customer's Ownership
A11: 0 | B11: =B2 -> 46162 | G11: =$E$5 -> 41120 | H11: =G11/$B$4 -> 0.8 | I11: =1-H11 -> 0.2
A12: 1 | B12: 46175 | C12: =B12-B11 -> 13 | D12: 0 | E12: =G11*B3/12*C12/30 -> 148.48889 | F12: 0 | G12: =$E$5 -> 41120 | H12: =G12/$B$4 -> 0.8 | I12: =1-H12 -> 0.2
A13: 1 | B13: =E2 -> 46205 | C13: =B13-B12 -> 30 | D13: =$E$3 -> 1326.8267 | E13: =G12*$B$3/12+E12 -> 491.15556 | F13: =D13-E13-E12 -> 687.18229 | G13: =G12-F13 -> 40432.818 | H13: =G13/$B$4 -> 0.78663069 | I13: =1-H13 -> 0.21336931
A14: 2 | B14: 46236 | C14: =B14-B13 -> 31 | D14: =$E$3 -> 1326.8267 | E14: =G13*$B$3/12 -> 336.94015 | F14: =D14-E14 -> 989.88659 | G14: =G13-F14 -> 39442.931 | H14: =G14/$B$4 -> 0.7673722 | I14: =1-H14 -> 0.2326278
A15: 3 | B15: 46267 | C15: =B15-B14 -> 31 | D15: =$E$3 -> 1326.8267 | E15: =G14*$B$3/12 -> 328.69109 | F15: =D15-E15 -> 998.13564 | G15: =G14-F15 -> 38444.795 | H15: =G15/$B$4 -> 0.74795322 | I15: =1-H15 -> 0.25204678
A16: 4 | B16: 46297 | C16: =B16-B15 -> 30 | D16: =$E$3 -> 1326.8267 | E16: =G15*$B$3/12 -> 320.3733 | F16: =D16-E16 -> 1006.4534 | G16: =G15-F16 -> 37438.342 | H16: =G16/$B$4 -> 0.72837241 | I16: =1-H16 -> 0.27162759
A17: 5 | B17: 46328 | C17: =B17-B16 -> 31 | D17: =$E$3 -> 1326.8267 | E17: =G16*$B$3/12 -> 311.98618 | F17: =D17-E17 -> 1014.8406 | G17: =G16-F17 -> 36423.501 | H17: =G17/$B$4 -> 0.70862843 | I17: =1-H17 -> 0.29137157
A18: 6 | B18: 46358 | C18: =B18-B17 -> 30 | D18: =$E$3 -> 1326.8267 | E18: =G17*$B$3/12 -> 303.52918 | F18: =D18-E18 -> 1023.2976 | G18: =G17-F18 -> 35400.204 | H18: =G18/$B$4 -> 0.68871992 | I18: =1-H18 -> 0.31128008
A19: 7 | B19: 46389 | C19: =B19-B18 -> 31 | D19: =$E$3 -> 1326.8267 | E19: =G18*$B$3/12 -> 295.0017 | F19: =D19-E19 -> 1031.825 | G19: =G18-F19 -> 34368.379 | H19: =G19/$B$4 -> 0.6686455 | I19: =1-H19 -> 0.3313545
A20: 8 | B20: 46420 | C20: =B20-B19 -> 31 | D20: =$E$3 -> 1326.8267 | E20: =G19*$B$3/12 -> 286.40316 | F20: =D20-E20 -> 1040.4236 | G20: =G19-F20 -> 33327.955 | H20: =G20/$B$4 -> 0.6484038 | I20: =1-H20 -> 0.3515962
A21: 9 | B21: 46448 | C21: =B21-B20 -> 28 | D21: =$E$3 -> 1326.8267 | E21: =G20*$B$3/12 -> 277.73296 | F21: =D21-E21 -> 1049.0938 | G21: =G20-F21 -> 32278.862 | H21: =G21/$B$4 -> 0.62799341 | I21: =1-H21 -> 0.37200659
A22: 10 | B22: 46479 | C22: =B22-B21 -> 31 | D22: =$E$3 -> 1326.8267 | E22: =G21*$B$3/12 -> 268.99051 | F22: =D22-E22 -> 1057.8362 | G22: =G21-F22 -> 31221.025 | H22: =G22/$B$4 -> 0.60741294 | I22: =1-H22 -> 0.39258706
A23: 11 | B23: 46509 | C23: =B23-B22 -> 30 | D23: =$E$3 -> 1326.8267 | E23: =G22*$B$3/12 -> 260.17521 | F23: =D23-E23 -> 1066.6515 | G23: =G22-F23 -> 30154.374 | H23: =G23/$B$4 -> 0.58666097 | I23: =1-H23 -> 0.41333903
A24: 12 | B24: 46540 | C24: =B24-B23 -> 31 | D24: =$E$3 -> 1326.8267 | E24: =G23*$B$3/12 -> 251.28645 | F24: =D24-E24 -> 1075.5403 | G24: =G23-F24 -> 29078.833 | H24: =G24/$B$4 -> 0.56573606 | I24: =1-H24 -> 0.43426394
A25: 13 | B25: 46570 | C25: =B25-B24 -> 30 | D25: =$E$3 -> 1326.8267 | E25: =G24*$B$3/12 -> 242.32361 | F25: =D25-E25 -> 1084.5031 | G25: =G24-F25 -> 27994.33 | H25: =G25/$B$4 -> 0.54463678 | I25: =1-H25 -> 0.45536322
... A47: 35 | B47: 47240 | C47: =B47-B46 -> 30 | D47: =$E$3 -> 1326.8267 | E47: =G46*$B$3/12 -> 25.094855 | F47: =D47-E47 -> 1301.7319 | G47: =G46-F47 -> 1709.6508 | H47: =G47/$B$4 -> 0.033261688 | I47: =1-H47 -> 0.96673831
A48: 36 | B48: 47271 | C48: =B48-B47 -> 31 | D48: =$E$3+489-92 -> 1723.8267 | E48: =G47*$B$3/12 -> 14.24709 | F48: =D48-E48 -> 1709.5796 | G48: =G47-F48 -> 0.071121589 | H48: =G48/$B$4 -> 1.3836885e-06 | I48: =1-H48 -> 0.99999862

Sheet Loan with deferral
A1: Scenario - 4 | B1: Due date and Disbursement date is on same day with Membership and user has opted for deferral of 3 months
A2: Date of Disbursement | B2: 46144 | D2: 1st Due Date | E2: 46175
A3: Profit / Rental % | B3: 0.055 | D3: PMT | E3: =PMT(B3/12,B7,-B6) -> 962.81807
A4: Vehicle Cost | B4: 51400 | D4: Method of computation | E4: non-compounding rental - for the deferral opted by the customer, there will be no additional rental charged to the customer on non-repayment. However, the interest will be collected after holiday is over
A5: Downpayment | B5: =10000 -> 10000
A6: Loan Amount | B6: =B4-B5 -> 41400
A7: Original Tenure | B7: 48 | C7: Months | D7: Updated Tenure | E7: 52
A11: Sr. No | B11: Date | C11: No. of days | D11: PMT Recovery | E11: Profit / Rental | F11: Principal | G11: Principal o/s | H11: Blox's Owership | I11: Customer's Owership
A12: 0 | B12: ='Disbursement and due date same'!$C$2 -> 46144 | G12: ='Disbursement and due date same'!$F$5 -> 41400 | H12: =$G12/$B$4 -> 0.80544747 | I12: =1-H12 -> 0.19455253
A13: 1 | B13: 46175 | C13: =B13-B12 -> 31 | D13: 0 | E13: =G12*$B$3/12 -> 189.75 | F13: 0 | G13: ='Disbursement and due date same'!$F$5 -> 41400 | H13: =$G13/$B$4 -> 0.80544747 | I13: =1-H13 -> 0.19455253
A14: 2 | B14: 46205 | C14: =B14-B13 -> 30 | D14: 0 | E14: =G13*$B$3/12 -> 189.75 | F14: 0 | G14: ='Disbursement and due date same'!$F$5 -> 41400 | H14: =$G14/$B$4 -> 0.80544747 | I14: =1-H14 -> 0.19455253
A15: 3 | B15: 46236 | C15: =B15-B14 -> 31 | D15: 0 | E15: =G14*$B$3/12 -> 189.75 | F15: 0 | G15: ='Disbursement and due date same'!$F$5 -> 41400 | H15: =$G15/$B$4 -> 0.80544747 | I15: =1-H15 -> 0.19455253
A16: 4 | B16: 46267 | C16: =B16-B15 -> 31 | D16: =$E$3 -> 962.81807 | E16: =(G15*$B$3/12)+SUM(E13:E15) -> 759 | F16: =D16-E16 -> 203.81807 | G16: =G12-F16 -> 41196.182 | H16: =$G16/$B$4 -> 0.80148214 | I16: =1-H16 -> 0.19851786
A17: 5 | B17: 46297 | C17: =B17-B16 -> 30 | D17: =$E$3 -> 962.81807 | E17: =G16*$B$3/12 -> 188.81583 | F17: =D17-E17 -> 774.00224 | G17: =G16-F17 -> 40422.18 | H17: =$G17/$B$4 -> 0.78642373 | I17: =1-H17 -> 0.21357627
A18: 6 | B18: 46328 | C18: =B18-B17 -> 31 | D18: =$E$3 -> 962.81807 | E18: =G17*$B$3/12 -> 185.26832 | F18: =D18-E18 -> 777.54975 | G18: =G17-F18 -> 39644.63 | H18: =$G18/$B$4 -> 0.7712963 | I18: =1-H18 -> 0.2287037
A19: 7 | B19: 46358 | C19: =B19-B18 -> 30 | D19: =$E$3 -> 962.81807 | E19: =G18*$B$3/12 -> 181.70455 | F19: =D19-E19 -> 781.11352 | G19: =G18-F19 -> 38863.516 | H19: =$G19/$B$4 -> 0.75609954 | I19: =1-H19 -> 0.24390046
A20: 8 | B20: 46389 | C20: =B20-B19 -> 31 | D20: =$E$3 -> 962.81807 | E20: =G19*$B$3/12 -> 178.12445 | F20: =D20-E20 -> 784.69362 | G20: =G19-F20 -> 38078.823 | H20: =$G20/$B$4 -> 0.74083313 | I20: =1-H20 -> 0.25916687
A21: 9 | B21: 46420 | C21: =B21-B20 -> 31 | D21: =$E$3 -> 962.81807 | E21: =G20*$B$3/12 -> 174.52794 | F21: =D21-E21 -> 788.29014 | G21: =G20-F21 -> 37290.533 | H21: =$G21/$B$4 -> 0.72549674 | I21: =1-H21 -> 0.27450326
A22: 10 | B22: 46448 | C22: =B22-B21 -> 28 | D22: =$E$3 -> 962.81807 | E22: =G21*$B$3/12 -> 170.91494 | F22: =D22-E22 -> 791.90313 | G22: =G21-F22 -> 36498.63 | H22: =$G22/$B$4 -> 0.71009007 | I22: =1-H22 -> 0.28990993
A23: 11 | B23: 46479 | C23: =B23-B22 -> 31 | D23: =$E$3 -> 962.81807 | E23: =G22*$B$3/12 -> 167.28539 | F23: =D23-E23 -> 795.53269 | G23: =G22-F23 -> 35703.097 | H23: =$G23/$B$4 -> 0.69461278 | I23: =1-H23 -> 0.30538722
A24: 12 | B24: 46509 | C24: =B24-B23 -> 30 | D24: =$E$3 -> 962.81807 | E24: =G23*$B$3/12 -> 163.63919 | F24: =D24-E24 -> 799.17888 | G24: =G23-F24 -> 34903.918 | H24: =$G24/$B$4 -> 0.67906455 | I24: =1-H24 -> 0.32093545
A25: 13 | B25: 46540 | C25: =B25-B24 -> 31 | D25: =$E$3 -> 962.81807 | E25: =G24*$B$3/12 -> 159.97629 | F25: =D25-E25 -> 802.84178 | G25: =G24-F25 -> 34101.076 | H25: =$G25/$B$4 -> 0.66344506 | I25: =1-H25 -> 0.33655494
A26: 14 | B26: 46570 | C26: =B26-B25 -> 30 | D26: =$E$3 -> 962.81807 | E26: =G25*$B$3/12 -> 156.2966 | F26: =D26-E26 -> 806.52148 | G26: =G25-F26 -> 33294.555 | H26: =$G26/$B$4 -> 0.64775398 | I26: =1-H26 -> 0.35224602
A27: 15 | B27: 46601 | C27: =B27-B26 -> 31 | D27: =$E$3 -> 962.81807 | E27: =G26*$B$3/12 -> 152.60004 | F27: =D27-E27 -> 810.21803 | G27: =G26-F27 -> 32484.337 | H27: =$G27/$B$4 -> 0.63199099 | I27: =1-H27 -> 0.36800901
A28: 16 | B28: 46632 | C28: =B28-B27 -> 31 | D28: =$E$3 -> 962.81807 | E28: =G27*$B$3/12 -> 148.88654 | F28: =D28-E28 -> 813.93153 | G28: =G27-F28 -> 31670.405 | H28: =$G28/$B$4 -> 0.61615574 | I28: =1-H28 -> 0.38384426
... A63: 51 | B63: 47697 | C63: =B63-B62 -> 31 | D63: =$E$3 -> 962.81807 | E63: =G62*$B$3/12 -> 7.6126578 | F63: =D63-E63 -> 955.20542 | G63: =G62-F63 -> 705.7381 | H63: =$G63/$B$4 -> 0.013730313 | I63: =1-H63 -> 0.98626969
A64: 52 | B64: 47729 | C64: =B64-B63 -> 32 | D64: =$E$3-254 -> 708.81807 | E64: =G63*$B$3/12 -> 3.234633 | F64: =D64-E64 -> 705.58344 | G64: =G63-F64 -> 0.15466292 | H64: =$G64/$B$4 -> 3.0090063e-06 | I64: =1-H64 -> 0.99999699

Sheet Part Payment received in BPI
A1: Scenario -5 | B1: Part Payment is made during BPI Period
A2: Date of Disbursement | B2: 46144 | D2: 1st Due Date | E2: 46175
A3: Profit / Rental % | B3: 0.1 | D3: PMT | E3: =PMT(B3/12,B7,-B6) -> 25813.75
A4: Vehicle Cost | B4: 1000000 | D4: Part Payment as on | E4: 46153
A5: Downpayment | B5: =20%*B4 -> 200000 | D5: Part Payment Amount | E5: 50000
A6: Loan Amount | B6: =B4-B5 -> 800000 | D6: Impact | E6: Reduction of Tenure by 2 months
A7: Tenure | B7: 36 | C7: Months
A11: Sr. No | B11: Date | C11: No. of days | D11: Total Recovery | E11: Rental Recovered | F11: Principal Recovered | G11: Principal o/s | H11: Blox's Ownership | I11: Customer's Ownership
A12: 0 | B12: ='Disbursement and due date same'!$C$2 -> 46144 | G12: =B6 -> 800000 | H12: =G12/$B$4 -> 0.8 | I12: =1-H12 -> 0.2
A13: 1 | B13: 46153 | C13: =B13-B12 -> 9 | D13: 50000 | E13: =G12*B3/12*C13/30 -> 2000 | F13: =D13-E13 -> 48000 | G13: =G12-F13 -> 752000 | H13: =G13/$B$4 -> 0.752 | I13: =1-H13 -> 0.248
A14: 1 | B14: 46175 | C14: =B14-B13 -> 22 | D14: =$E$3 -> 25813.75 | E14: =$G13*$B$3/12*$C14/30 -> 4595.5556 | F14: =D14-E14 -> 21218.194 | G14: =G13-F14 -> 730781.81 | H14: =G14/$B$4 -> 0.73078181 | I14: =1-H14 -> 0.26921819
A15: 2 | B15: 46205 | C15: =B15-B14 -> 30 | D15: =$E$3 -> 25813.75 | E15: =G14*$B$3/12 -> 6089.8484 | F15: =D15-E15 -> 19723.901 | G15: =G14-F15 -> 711057.9 | H15: =G15/$B$4 -> 0.7110579 | I15: =1-H15 -> 0.2889421
A16: 3 | B16: 46236 | C16: =B16-B15 -> 31 | D16: =$E$3 -> 25813.75 | E16: =G15*$B$3/12 -> 5925.4825 | F16: =D16-E16 -> 19888.267 | G16: =G15-F16 -> 691169.64 | H16: =G16/$B$4 -> 0.69116964 | I16: =1-H16 -> 0.30883036
A17: 4 | B17: 46267 | C17: =B17-B16 -> 31 | D17: =$E$3 -> 25813.75 | E17: =G16*$B$3/12 -> 5759.747 | F17: =D17-E17 -> 20054.003 | G17: =G16-F17 -> 671115.63 | H17: =G17/$B$4 -> 0.67111563 | I17: =1-H17 -> 0.32888437
A18: 5 | B18: 46297 | C18: =B18-B17 -> 30 | D18: =$E$3 -> 25813.75 | E18: =G17*$B$3/12 -> 5592.6303 | F18: =D18-E18 -> 20221.119 | G18: =G17-F18 -> 650894.51 | H18: =G18/$B$4 -> 0.65089451 | I18: =1-H18 -> 0.34910549
A19: 6 | B19: 46328 | C19: =B19-B18 -> 31 | D19: =$E$3 -> 25813.75 | E19: =G18*$B$3/12 -> 5424.121 | F19: =D19-E19 -> 20389.629 | G19: =G18-F19 -> 630504.89 | H19: =G19/$B$4 -> 0.63050489 | I19: =1-H19 -> 0.36949511
A20: 7 | B20: 46358 | C20: =B20-B19 -> 30 | D20: =$E$3 -> 25813.75 | E20: =G19*$B$3/12 -> 5254.2074 | F20: =D20-E20 -> 20559.542 | G20: =G19-F20 -> 609945.34 | H20: =G20/$B$4 -> 0.60994534 | I20: =1-H20 -> 0.39005466
A21: 8 | B21: 46389 | C21: =B21-B20 -> 31 | D21: =$E$3 -> 25813.75 | E21: =G20*$B$3/12 -> 5082.8779 | F21: =D21-E21 -> 20730.872 | G21: =G20-F21 -> 589214.47 | H21: =G21/$B$4 -> 0.58921447 | I21: =1-H21 -> 0.41078553
A22: 9 | B22: 46420 | C22: =B22-B21 -> 31 | D22: =$E$3 -> 25813.75 | E22: =G21*$B$3/12 -> 4910.1206 | F22: =D22-E22 -> 20903.629 | G22: =G21-F22 -> 568310.84 | H22: =G22/$B$4 -> 0.56831084 | I22: =1-H22 -> 0.43168916
A23: 10 | B23: 46448 | C23: =B23-B22 -> 28 | D23: =$E$3 -> 25813.75 | E23: =G22*$B$3/12 -> 4735.9237 | F23: =D23-E23 -> 21077.826 | G23: =G22-F23 -> 547233.02 | H23: =G23/$B$4 -> 0.54723302 | I23: =1-H23 -> 0.45276698
A24: 11 | B24: 46479 | C24: =B24-B23 -> 31 | D24: =$E$3 -> 25813.75 | E24: =G23*$B$3/12 -> 4560.2751 | F24: =D24-E24 -> 21253.475 | G24: =G23-F24 -> 525979.54 | H24: =G24/$B$4 -> 0.52597954 | I24: =1-H24 -> 0.47402046
A25: 12 | B25: 46509 | C25: =B25-B24 -> 30 | D25: =$E$3 -> 25813.75 | E25: =G24*$B$3/12 -> 4383.1629 | F25: =D25-E25 -> 21430.587 | G25: =G24-F25 -> 504548.96 | H25: =G25/$B$4 -> 0.50454896 | I25: =1-H25 -> 0.49545104
A26: 13 | B26: 46540 | C26: =B26-B25 -> 31 | D26: =$E$3 -> 25813.75 | E26: =G25*$B$3/12 -> 4204.5746 | F26: =D26-E26 -> 21609.175 | G26: =G25-F26 -> 482939.78 | H26: =G26/$B$4 -> 0.48293978 | I26: =1-H26 -> 0.51706022
... A46: 33 | B46: 47151 | C46: =B46-B45 -> 31 | D46: =$E$3 -> 25813.75 | E46: =G45*$B$3/12 -> 303.14967 | F46: =D46-E46 -> 25510.6 | G46: =G45-F46 -> 10867.361 | H46: =G46/$B$4 -> 0.010867361 | I46: =1-H46 -> 0.98913264
A47: 34 | B47: 47179 | C47: =B47-B46 -> 28 | D47: =$E$3-14915 -> 10898.75 | E47: =G46*$B$3/12 -> 90.561339 | F47: =D47-E47 -> 10808.188 | G47: =G46-F47 -> 59.1723 | H47: =G47/$B$4 -> 5.91723e-05 | I47: =1-H47 -> 0.99994083

Sheet PP after BPI
A1: Scenario -6 | B1: Part Payment is made after BPI Period
A2: Date of Disbursement | B2: 46147 | D2: 1st Due Date | E2: 46178
A3: Profit / Rental % | B3: 0.1 | D3: PMT | E3: =PMT(B3/12,B7,-B6) -> 25813.75
A4: Vehicle Cost | B4: 1000000 | D4: Part Payment as on | E4: 46306
A5: Downpayment | B5: =20%*B4 -> 200000 | D5: Part Payment Amount | E5: 50000
A6: Loan Amount | B6: =B4-B5 -> 800000 | D6: Impact | E6: Reduction of Tenure by 2 months
A7: Tenure | B7: 36 | C7: Months
A11: Sr. No | B11: Date | C11: No. of days | D11: Total Recovery | E11: Rental Recovered | F11: Principal Recovered | G11: Principal o/s | H11: Blox's Ownership | I11: Customer's Ownership
A12: 0 | B12: ='Disbursement and due date same'!$C$2 -> 46144 | G12: =$B$6 -> 800000 | H12: =G12/$B$4 -> 0.8 | I12: =1-H12 -> 0.2
A13: 1 | B13: 46178 | C13: =B13-B12 -> 34 | D13: =$E$3 -> 25813.75 | E13: =G12*$B$3/12 -> 6666.6667 | F13: =D13-E13 -> 19147.083 | G13: =G12-F13 -> 780852.92 | H13: =G13/$B$4 -> 0.78085292 | I13: =1-H13 -> 0.21914708
A14: 2 | B14: 46208 | C14: =B14-B13 -> 30 | D14: =$E$3 -> 25813.75 | E14: =G13*$B$3/12 -> 6507.1076 | F14: =D14-E14 -> 19306.642 | G14: =G13-F14 -> 761546.27 | H14: =G14/$B$4 -> 0.76154627 | I14: =1-H14 -> 0.23845373
A15: 3 | B15: 46239 | C15: =B15-B14 -> 31 | D15: =$E$3 -> 25813.75 | E15: =G14*$B$3/12 -> 6346.219 | F15: =D15-E15 -> 19467.531 | G15: =G14-F15 -> 742078.74 | H15: =G15/$B$4 -> 0.74207874 | I15: =1-H15 -> 0.25792126
A16: 4 | B16: 46270 | C16: =B16-B15 -> 31 | D16: =$E$3 -> 25813.75 | E16: =G15*$B$3/12 -> 6183.9895 | F16: =D16-E16 -> 19629.76 | G16: =G15-F16 -> 722448.98 | H16: =G16/$B$4 -> 0.72244898 | I16: =1-H16 -> 0.27755102
A17: 5 | B17: 46300 | C17: =B17-B16 -> 30 | D17: =$E$3 -> 25813.75 | E17: =G16*$B$3/12 -> 6020.4082 | F17: =D17-E17 -> 19793.342 | G17: =G16-F17 -> 702655.64 | H17: =G17/$B$4 -> 0.70265564 | I17: =1-H17 -> 0.29734436
A18: 6 | B18: =E4 -> 46306 | C18: =B18-B17 -> 6 | D18: 50000 | E18: =G17*B3/12*C18/30 -> 1171.0927 | F18: =D18-E18 -> 48828.907 | G18: =G17-F18 -> 653826.73 | H18: =G18/$B$4 -> 0.65382673 | I18: =1-H18 -> 0.34617327
A19: 6 | B19: 46331 | C19: =B19-B18 -> 25 | D19: =$E$3 -> 25813.75 | E19: =G18*$B$3/12 -> 5448.5561 | F19: =D19-E19 -> 20365.194 | G19: =G18-F19 -> 633461.54 | H19: =G19/$B$4 -> 0.63346154 | I19: =1-H19 -> 0.36653846
A20: 7 | B20: 46361 | C20: =B20-B19 -> 30 | D20: =$E$3 -> 25813.75 | E20: =G19*$B$3/12 -> 5278.8462 | F20: =D20-E20 -> 20534.904 | G20: =G19-F20 -> 612926.64 | H20: =G20/$B$4 -> 0.61292664 | I20: =1-H20 -> 0.38707336
A21: 8 | B21: 46392 | C21: =B21-B20 -> 31 | D21: =$E$3 -> 25813.75 | E21: =G20*$B$3/12 -> 5107.722 | F21: =D21-E21 -> 20706.028 | G21: =G20-F21 -> 592220.61 | H21: =G21/$B$4 -> 0.59222061 | I21: =1-H21 -> 0.40777939
A22: 9 | B22: 46423 | C22: =B22-B21 -> 31 | D22: =$E$3 -> 25813.75 | E22: =G21*$B$3/12 -> 4935.1717 | F22: =D22-E22 -> 20878.578 | G22: =G21-F22 -> 571342.03 | H22: =G22/$B$4 -> 0.57134203 | I22: =1-H22 -> 0.42865797
A23: 10 | B23: 46451 | C23: =B23-B22 -> 28 | D23: =$E$3 -> 25813.75 | E23: =G22*$B$3/12 -> 4761.1836 | F23: =D23-E23 -> 21052.566 | G23: =G22-F23 -> 550289.47 | H23: =G23/$B$4 -> 0.55028947 | I23: =1-H23 -> 0.44971053
A24: 11 | B24: 46482 | C24: =B24-B23 -> 31 | D24: =$E$3 -> 25813.75 | E24: =G23*$B$3/12 -> 4585.7455 | F24: =D24-E24 -> 21228.004 | G24: =G23-F24 -> 529061.46 | H24: =G24/$B$4 -> 0.52906146 | I24: =1-H24 -> 0.47093854
A25: 12 | B25: 46512 | C25: =B25-B24 -> 30 | D25: =$E$3 -> 25813.75 | E25: =G24*$B$3/12 -> 4408.8455 | F25: =D25-E25 -> 21404.904 | G25: =G24-F25 -> 507656.56 | H25: =G25/$B$4 -> 0.50765656 | I25: =1-H25 -> 0.49234344
A26: 13 | B26: 46543 | C26: =B26-B25 -> 31 | D26: =$E$3 -> 25813.75 | E26: =G25*$B$3/12 -> 4230.4713 | F26: =D26-E26 -> 21583.278 | G26: =G25-F26 -> 486073.28 | H26: =G26/$B$4 -> 0.48607328 | I26: =1-H26 -> 0.51392672
A27: 14 | B27: 46573 | C27: =B27-B26 -> 30 | D27: =$E$3 -> 25813.75 | E27: =G26*$B$3/12 -> 4050.6107 | F27: =D27-E27 -> 21763.139 | G27: =G26-F27 -> 464310.14 | H27: =G27/$B$4 -> 0.46431014 | I27: =1-H27 -> 0.53568986
A28: 15 | B28: 46604 | C28: =B28-B27 -> 31 | D28: =$E$3 -> 25813.75 | E28: =G27*$B$3/12 -> 3869.2512 | F28: =D28-E28 -> 21944.499 | G28: =G27-F28 -> 442365.64 | H28: =G28/$B$4 -> 0.44236564 | I28: =1-H28 -> 0.55763436
A29: 16 | B29: 46635 | C29: =B29-B28 -> 31 | D29: =$E$3 -> 25813.75 | E29: =G28*$B$3/12 -> 3686.3803 | F29: =D29-E29 -> 22127.369 | G29: =G28-F29 -> 420238.27 | H29: =G29/$B$4 -> 0.42023827 | I29: =1-H29 -> 0.57976173
A30: 17 | B30: 46665 | C30: =B30-B29 -> 30 | D30: =$E$3 -> 25813.75 | E30: =G29*$B$3/12 -> 3501.9856 | F30: =D30-E30 -> 22311.764 | G30: =G29-F30 -> 397926.51 | H30: =G30/$B$4 -> 0.39792651 | I30: =1-H30 -> 0.60207349
... A46: 33 | B46: 47154 | C46: =B46-B45 -> 31 | D46: =$E$3 -> 25813.75 | E46: =G45*$B$3/12 -> 333.72187 | F46: =D46-E46 -> 25480.028 | G46: =G45-F46 -> 14566.597 | H46: =G46/$B$4 -> 0.014566597 | I46: =1-H46 -> 0.9854334
A47: 34 | B47: 47182 | C47: =B47-B46 -> 28 | D47: =$E$3-11126 -> 14687.75 | E47: =G46*$B$3/12 -> 121.38831 | F47: =D47-E47 -> 14566.361 | G47: =G46-F47 -> 0.23519371 | H47: =G47/$B$4 -> 2.3519371e-07 | I47: =1-H47 -> 0.99999976
D48: Odd Amount Adjustment

Sheet Foreclosure of loan
A1: Scenario - 7 | B1: Foreclosure of loan
A2: Date of Disbursement | B2: 46144 | D2: 1st Due Date | E2: 46175
A3: Profit / Rental % | B3: 0.1 | D3: PMT | E3: =PMT(B3/12,B7,-B6) -> 25813.75
A4: Vehicle Cost | B4: 1000000 | D4: Foreclosure Date | E4: 46306
A5: Downpayment | B5: =20%*B4 -> 200000
A6: Loan Amount | B6: =B4-B5 -> 800000
A7: Original Tenure | B7: 36 | C7: Months | D7: Tenure after foreclosure | E7: =A18 -> 6
A11: Sr. No | B11: Date | C11: No. of days | D11: Total Recovery | E11: Rental Recovered | F11: Principal Recovered | G11: Principal o/s | H11: Blox's Share | I11: Customer' Share
A12: 0 | B12: 46144 | F12: =D12-E12 -> 0 | G12: =B6 -> 800000 | H12: =G12/$B$4 -> 0.8 | I12: =1-H12 -> 0.2
A13: 1 | B13: 46175 | C13: =B13-B12 -> 31 | D13: =$E$3 -> 25813.75 | E13: =(G12*B3/12*C13/30)+E12 -> 6888.8889 | F13: =D13-E13 -> 18924.861 | G13: =G12-F13 -> 781075.14 | H13: =G13/$B$4 -> 0.78107514 | I13: =1-H13 -> 0.21892486
A14: 2 | B14: 46205 | C14: =B14-B13 -> 30 | D14: =$E$3 -> 25813.75 | E14: =G13*$B$3/12 -> 6508.9595 | F14: =D14-E14 -> 19304.79 | G14: =G13-F14 -> 761770.35 | H14: =G14/$B$4 -> 0.76177035 | I14: =1-H14 -> 0.23822965
A15: 3 | B15: 46236 | C15: =B15-B14 -> 31 | D15: =$E$3 -> 25813.75 | E15: =G14*$B$3/12 -> 6348.0862 | F15: =D15-E15 -> 19465.664 | G15: =G14-F15 -> 742304.69 | H15: =G15/$B$4 -> 0.74230469 | I15: =1-H15 -> 0.25769531
A16: 4 | B16: 46267 | C16: =B16-B15 -> 31 | D16: =$E$3 -> 25813.75 | E16: =G15*$B$3/12 -> 6185.8724 | F16: =D16-E16 -> 19627.877 | G16: =G15-F16 -> 722676.81 | H16: =G16/$B$4 -> 0.72267681 | I16: =1-H16 -> 0.27732319
A17: 5 | B17: 46297 | C17: =B17-B16 -> 30 | D17: =$E$3 -> 25813.75 | E17: =G16*$B$3/12 -> 6022.3067 | F17: =D17-E17 -> 19791.443 | G17: =G16-F17 -> 702885.36 | H17: =G17/$B$4 -> 0.70288536 | I17: =1-H17 -> 0.29711464
A18: 6 | B18: 46328 | C18: =B18-B17 -> 31 | D18: =G17+E18 -> 708937.99 | E18: =G17*B3/12*C18/30 -> 6052.624 | F18: =D18-E18 -> 702885.36 | G18: =F18-G17 -> 0 | H18: =G18/$B$4 -> 0 | I18: =1-H18 -> 1

Sheet OTS and Write off
A1: Scenario - 8 | B1: Foreclosure of loan
A2: Date of Disbursement | B2: 46144 | D2: 1st Due Date | E2: 46175
A3: Profit / Rental % | B3: 0.1 | D3: PMT | E3: =PMT(B3/12,B7,-B6) -> 25813.75
A4: Vehicle Cost | B4: 1000000 | D4: One time settlment | E4: 46306
A5: Downpayment | B5: =20%*B4 -> 200000 | D5: Settlement Amount | E5: 500000
A6: Loan Amount | B6: =B4-B5 -> 800000
A7: Tenure | B7: 36 | C7: Months
A11: Sr. No | B11: Date | C11: No. of days | D11: Total Recovery | E11: Rental Recovered | F11: Principal Recovered | G11: Principal o/s | H11: Blox's Share | I11: Customer's Share
A12: 0 | B12: =B2 -> 46144 | G12: =B6 -> 800000 | H12: =G12/$B$4 -> 0.8 | I12: =1-H12 -> 0.2
A13: 1 | B13: 46175 | C13: =B13-B12 -> 31 | D13: =$E$3 -> 25813.75 | E13: =G12*$B$3/12 -> 6666.6667 | F13: =D13-E13 -> 19147.083 | G13: =G12-F13 -> 780852.92 | H13: =G13/$B$4 -> 0.78085292 | I13: =1-H13 -> 0.21914708
A14: 2 | B14: 46205 | C14: =B14-B13 -> 30 | D14: =$E$3 -> 25813.75 | E14: =G13*$B$3/12 -> 6507.1076 | F14: =D14-E14 -> 19306.642 | G14: =G13-F14 -> 761546.27 | H14: =G14/$B$4 -> 0.76154627 | I14: =1-H14 -> 0.23845373
A15: 3 | B15: 46236 | C15: =B15-B14 -> 31 | D15: =$E$3 -> 25813.75 | E15: =G14*$B$3/12 -> 6346.219 | F15: =D15-E15 -> 19467.531 | G15: =G14-F15 -> 742078.74 | H15: =G15/$B$4 -> 0.74207874 | I15: =1-H15 -> 0.25792126
A16: 4 | B16: 46267 | C16: =B16-B15 -> 31 | D16: =$E$3 -> 25813.75 | E16: =G15*$B$3/12 -> 6183.9895 | F16: =D16-E16 -> 19629.76 | G16: =G15-F16 -> 722448.98 | H16: =G16/$B$4 -> 0.72244898 | I16: =1-H16 -> 0.27755102
A17: 5 | B17: 46297 | C17: =B17-B16 -> 30 | D17: =$E$3 -> 25813.75 | E17: =G16*$B$3/12 -> 6020.4082 | F17: =D17-E17 -> 19793.342 | G17: =G16-F17 -> 702655.64 | H17: =G17/$B$4 -> 0.70265564 | I17: =1-H17 -> 0.29734436
A18: 6 | B18: =E4 -> 46306 | C18: =B18-B17 -> 9 | D18: 500000 | E18: 0 | F18: =D18-E18 -> 500000 | G18: =G17-F18 -> 202655.64 | H18: =F18/$B$4 -> 0.5 | I18: =1-H18 -> 0.5
E20: =$G$17*$B$3/12*$C$18/30 -> 1756.6391 | F20: will be written off Interest
E21: =G18 -> 202655.64 | F21: will be written off Principal
